libraryshad/An_Wb.py
libraryshad/Socket.py
libraryshad/__init__.py
libraryshad/encryption.py
libraryshad/matn.py
libraryshad/shad.py
shadbot-1.0.3.dist-info/LICENCE
shadbot-1.0.3.dist-info/METADATA
shadbot-1.0.3.dist-info/WHEEL
shadbot-1.0.3.dist-info/top_level.txt
shadbot-1.0.3.dist-info/RECORD
