Metadata-Version: 2.1
Name: shadbot
Version: 1.0.3
Summary: Another example of the library making the Rubik's robot
Home-page: https://rubika.ir/python_java_source
Author: mamadcoder
Author-email: mamadcoder@gmail.com
License: MIT
Keywords: rubika,bot,robot,library,rubikalib,rubikalib.ml,rubikalib.ir,rubika.ir,Rubika,Python,rubiran,pyrubika
Classifier: Development Status :: 3 - Alpha
Classifier: Intended Audience :: Developers
Classifier: Topic :: Software Development :: Build Tools
Classifier: License :: OSI Approved :: MIT License
Classifier: Programming Language :: Python :: Implementation :: PyPy
Classifier: Programming Language :: Python :: 3
Classifier: Programming Language :: Python :: 3.4
Classifier: Programming Language :: Python :: 3.5
Classifier: Programming Language :: Python :: 3.6
Classifier: Programming Language :: Python :: 3.7
Classifier: Programming Language :: Python :: 3.8
Classifier: Programming Language :: Python :: 3.9
Classifier: Programming Language :: Python :: 3.10
License-File: LICENCE
